copilot_toolkit/__init__.py
copilot_toolkit/agent.py
copilot_toolkit/code_collector.py
copilot_toolkit/main.py
copilot_toolkit/model.py
copilot_toolkit/reporting.py
copilot_toolkit/collector/__init__.py
copilot_toolkit/collector/analysis.py
copilot_toolkit/collector/config.py
copilot_toolkit/collector/discovery.py
copilot_toolkit/collector/metrics.py
copilot_toolkit/collector/reporting.py
copilot_toolkit/collector/utils.py
copilot_toolkit/guides/copilot.md
copilot_toolkit/guides/cursor.md
copilot_toolkit/prompts/app.md
copilot_toolkit/prompts/llms-ctx.txt
copilot_toolkit/prompts/project.md
copilot_toolkit/prompts/specs.md
copilot_toolkit/prompts/task.md
copilot_toolkit/templates/cursor/rules/auto-commit.mdc
copilot_toolkit/templates/cursor/rules/global-workflow.mdc
copilot_toolkit/templates/cursor/rules/init-project.mdc
copilot_toolkit/templates/cursor/rules/init-specs.mdc
copilot_toolkit/templates/cursor/rules/init-tasks.mdc
copilot_toolkit/templates/cursor/rules/specs-definition.mdc
copilot_toolkit/templates/cursor/rules/tasks-definition.mdc
copilot_toolkit/templates/github/copilot-instructions.md
copilot_toolkit/templates/github/prompts/init-project.prompt.md
copilot_toolkit/templates/github/prompts/init-specs.prompt.md
copilot_toolkit/templates/github/prompts/init-tasks.prompt.md
copilot_toolkit/templates/github/prompts/specs-definition.md
copilot_toolkit/templates/github/prompts/tasks-definition.md
copilot_toolkit/utils/cli_helper.py
copilot_toolkit-0.2.14.dist-info/METADATA
copilot_toolkit-0.2.14.dist-info/WHEEL
copilot_toolkit-0.2.14.dist-info/entry_points.txt
copilot_toolkit-0.2.14.dist-info/RECORD
