Metadata-Version: 2.4
Name: copilot-toolkit
Version: 0.2.14
Summary: 🚀 A toolkit for coding agents 🚀 Get the most out of GitHub Copilot, Cursor and Co. Powered by flock.
Author-email: Andre Ratzenberger <andre.ratzenberger@whiteduck.de>
Requires-Python: >=3.10
Requires-Dist: flock-core>=0.3.38
Requires-Dist: questionary>=2.1.0
Requires-Dist: radon>=6.0.1
Requires-Dist: rich>=13.9.4
Requires-Dist: tomli>=2.0.1
